lotc/__init__.py
lotc/main.py
lotc/utils.py
lotc/commands/__init__.py
lotc/commands/download.py
lotc/commands/merge.py
lotc/commands/trim.py
lord_of_the_clips-0.1.12.dist-info/LICENSE
lord_of_the_clips-0.1.12.dist-info/METADATA
lord_of_the_clips-0.1.12.dist-info/WHEEL
lord_of_the_clips-0.1.12.dist-info/entry_points.txt
lord_of_the_clips-0.1.12.dist-info/top_level.txt
lord_of_the_clips-0.1.12.dist-info/RECORD
