Metadata-Version: 2.1
Name: lord-of-the-clips
Version: 0.1.12
Summary: 🎥✂️🔗 Video downloader, trimmer, and merger using the terminal. Supports YouTube, Facebook, Reddit, Twitter, TikTok, Instagram, LinkedIn, 9GAG, etc. Downloads/trims at multiple points. Merges multiple clips.
Home-page: https://github.com/ranelpadon/lord-of-the-clips
Author: Ranel Padon
Author-email: ranel.padon@gmail.com
License: MIT
Keywords: video,downloader,trimmer,snipper,cutter,merger,splicer,cli,terminal,youtube,facebook,reddit,twitter,multiple,click,rich,movie,snip,clip,subclip
Platform: Windows
Platform: macOS
Platform: Linux
Classifier: Intended Audience :: Developers
Classifier: Intended Audience :: End Users/Desktop
Classifier: License :: OSI Approved :: MIT License
Classifier: Operating System :: MacOS
Classifier: Operating System :: Microsoft :: Windows
Classifier: Operating System :: POSIX
Classifier: Operating System :: POSIX :: Linux
Classifier: Programming Language :: Python
Classifier: Programming Language :: Python :: 3.7
Classifier: Programming Language :: Python :: 3.8
Classifier: Programming Language :: Python :: 3.9
Classifier: Programming Language :: Python :: 3.10
Classifier: Programming Language :: Python :: 3.11
Classifier: Programming Language :: Python :: 3 :: Only
Classifier: Topic :: Software Development
Classifier: Topic :: Utilities
Requires-Python: >=3.7
License-File: LICENSE
Requires-Dist: click (>=8.1.3)
Requires-Dist: delegator.py (>=0.1.1)
Requires-Dist: halo (>=0.0.31)
Requires-Dist: moviepy (>=1.0.3)
Requires-Dist: requests (>=2.28.1)
Requires-Dist: rich (>=13.0.1)
Requires-Dist: rich-click (>=1.6.1)
Requires-Dist: yt-dlp (>=2023.2.17)
